[
    {
        "aqi":123,
        "idx":11848,
        "url":"http://cpcb.nic.in/",
        "name":"CPCB - India Central Pollution Control Board",
        "logo":"India-CPCB.png",
        "co":7.1,
        "dew":17,
        "h":51.94,
        "NO2":17,
        "o3":2.2,
        "p":1003,
        "pm10":128,
        "pm25":160,
        "so2":14.1,
        "t":31,
        "w":1.1475,
        "wg":8.7,
        "sync":"2022-05-19T08:07:15+09:00"
        },

        {
            "aqi":123,
        "idx":11848,
        "url":"http://cpcb.nic.in/",
        "name":"CPCB - India Central Pollution Control Board",
        "logo":"India-CPCB.png",
        "co":7.1,
        "dew":17,
        "h":51.94,
        "NO2":21,
        "o3":2.2,
        "p":1003,
        "pm10":128,
        "pm25":160,
        "so2":14.1,
        "t":31,
        "w":1.1475,
        "wg":8.7,
        "sync":"2022-05-19T08:07:15+09:00"
            },

            {"aqi":123,
                "idx":11848,
                "url":"http://cpcb.nic.in/",
                "name":"CPCB - India Central Pollution Control Board",
                "logo":"India-CPCB.png",
                "co":7.1,
                "dew":17,
                "h":51.94,
                "NO2":20,
                "o3":2.2,
                "p":1003,
                "pm10":128,
                "pm25":160,
                "so2":14.1,
                "t":31,
                "w":1.1475,
                "wg":8.7,
                "sync":"2022-05-19T08:07:15+09:00"
                },

                {
                    "aqi":123,
                    "idx":11848,
                    "url":"http://cpcb.nic.in/",
                    "name":"CPCB - India Central Pollution Control Board",
                    "logo":"India-CPCB.png",
                    "co":7.1,
                    "dew":17,
                    "h":51.94,
                    "NO2":23,
                    "o3":2.2,
                    "p":1003,
                    "pm10":128,
                    "pm25":160,
                    "so2":14.1,
                    "t":31,
                    "w":1.1475,
                    "wg":8.7,
                    "sync":"2022-05-19T08:07:15+09:00"
                    },

                    {
                        "aqi":123,
                        "idx":11848,
                        "url":"http://cpcb.nic.in/",
                        "name":"CPCB - India Central Pollution Control Board",
                        "logo":"India-CPCB.png",
                        "co":7.1,
                        "dew":19,
                        "h":51.94,
                        "NO2":17,
                        "o3":2.2,
                        "p":1003,
                        "pm10":128,
                        "pm25":160,
                        "so2":14.1,
                        "t":31,
                        "w":1.1475,
                        "wg":8.7,
                        "sync":"2022-05-19T08:07:15+09:00"
                        }
    
]